welltestpy/__init__.py
welltestpy/_version.py
welltestpy/data/__init__.py
welltestpy/data/campaignlib.py
welltestpy/data/data_io.py
welltestpy/data/testslib.py
welltestpy/data/varlib.py
welltestpy/estimate/__init__.py
welltestpy/estimate/estimators.py
welltestpy/estimate/spotpylib.py
welltestpy/estimate/steady_lib.py
welltestpy/estimate/transient_lib.py
welltestpy/process/__init__.py
welltestpy/process/processlib.py
welltestpy/tools/__init__.py
welltestpy/tools/diagnostic_plots.py
welltestpy/tools/plotter.py
welltestpy/tools/trilib.py
welltestpy-1.2.0.dist-info/METADATA
welltestpy-1.2.0.dist-info/WHEEL
welltestpy-1.2.0.dist-info/licenses/LICENSE
welltestpy-1.2.0.dist-info/RECORD
