Metadata-Version: 2.1
Name: welltestpy
Version: 1.2.0
Summary: welltestpy - package to handle well-based Field-campaigns.
Project-URL: Homepage, https://github.com/GeoStat-Framework/welltestpy
Project-URL: Documentation, https://welltestpy.readthedocs.io
Project-URL: Source, https://github.com/GeoStat-Framework/welltestpy
Project-URL: Tracker, https://github.com/GeoStat-Framework/welltestpy/issues
Project-URL: Changelog, https://github.com/GeoStat-Framework/welltestpy/blob/main/CHANGELOG.md
Project-URL: Conda-Forge, https://anaconda.org/conda-forge/welltestpy
Author-email: "Sebastian Müller, Jarno Herrmann" <info@geostat-framework.org>
License-Expression: MIT
License-File: LICENSE
Classifier: Development Status :: 5 - Production/Stable
Classifier: Intended Audience :: Developers
Classifier: Intended Audience :: End Users/Desktop
Classifier: Intended Audience :: Science/Research
Classifier: License :: OSI Approved :: MIT License
Classifier: Natural Language :: English
Classifier: Operating System :: MacOS
Classifier: Operating System :: MacOS :: MacOS X
Classifier: Operating System :: Microsoft
Classifier: Operating System :: Microsoft :: Windows
Classifier: Operating System :: POSIX
Classifier: Operating System :: Unix
Classifier: Programming Language :: Python
Classifier: Programming Language :: Python :: 3
Classifier: Programming Language :: Python :: 3 :: Only
Classifier: Programming Language :: Python :: 3.6
Classifier: Programming Language :: Python :: 3.7
Classifier: Programming Language :: Python :: 3.8
Classifier: Programming Language :: Python :: 3.9
Classifier: Topic :: Scientific/Engineering
Classifier: Topic :: Software Development
Classifier: Topic :: Utilities
Requires-Python: >=3.7
Requires-Dist: anaflow>=1.0.0
Requires-Dist: matplotlib>=3.0.0
Requires-Dist: numpy>=1.14.5
Requires-Dist: packaging>=20
Requires-Dist: scipy>=1.1.0
Requires-Dist: spotpy>=1.5.0
Provides-Extra: check
Requires-Dist: black<24,>=23; extra == 'check'
Requires-Dist: isort[colors]<6; extra == 'check'
Requires-Dist: pylint<3; extra == 'check'
Provides-Extra: doc
Requires-Dist: m2r2>=0.2.8; extra == 'doc'
Requires-Dist: numpydoc>=1.1; extra == 'doc'
Requires-Dist: sphinx-gallery>=0.8; extra == 'doc'
Requires-Dist: sphinx-rtd-theme<1.1,>=1; extra == 'doc'
Requires-Dist: sphinx>=4; extra == 'doc'
Provides-Extra: test
Requires-Dist: pytest-cov>=3; extra == 'test'
